{
  "name": "Hypnotize",
  "artist": "System of a Down",
  "transcriber": "PianoTomas",
  "instrument": "Piano",
  "notes": [
    "B:225",
    "F#:225",
    "B:224",
    "F#:225",
    "C#+:225",
    "F#:225",
    "C#+:225",
    "F#:224",
    "C#+:224",
    "F#:224",
    "C#+:224",
    "F#:224",
    "C#+:224",
    "F#:225",
    "C#+:224",
    "F#:224",
    "D+:224",
    "F#:224",
    "D+:224",
    "F#:224",
    "C#+:224",
    "F#:224",
    "C#+:224",
    "F#:224",
    "B:224",
    "F#:224",
    "B:225",
    "F#:225",
    "A#:225",
    "F#:225",
    "A#:225",
    "F#:225",
    "B:225",
    "F#:225",
    "B:225",
    "F#:225",
    "C#+:225",
    "F#:225",
    "C#+:225",
    "F#:225",
    "C#+:225",
    "F#:225",
    "C#+:225",
    "F#:225",
    "C#+:225",
    "F#:225",
    "C#+:225",
    "F#:225",
    "D+:225",
    "F#:225",
    "D+:225",
    "F#:225",
    "C#+:225",
    "F#:225",
    "C#+:225",
    "F#:225",
    "B:225",
    "F#:225",
    "B:225",
    "F#:225",
    "A#:225",
    "F#:225",
    "A#:225",
    "F#:225",
    "F#:375",
    "F#:375",
    "F:375",
    "F:375",
    "G#:375",
    "G#:375",
    "F#:375",
    "F#:375",
    "A#:375",
    "A#:375",
    "G#:375",
    "G#:375",
    "B:375",
    "B:375",
    "A#:375",
    "A#:375",
    "F#:375",
    "F#:375",
    "F:375",
    "F:375",
    "G#:375",
    "G#:375",
    "F#:375",
    "F#:375",
    "A#:375",
    "A#:375",
    "G#:375",
    "G#:375",
    "B:375",
    "B:375",
    "A#:375",
    "A#:375",
    "C#+:375",
    "C#+:375",
    "B:375",
    "B:375",
    "A#:375",
    "A#:375",
    "G#:375",
    "G#:375",
    "B:375",
    "B:375",
    "A#:375",
    "A#:375",
    "G#:375",
    "G#:375",
    "F#:375",
    "F#:375",
    "A:375",
    "A:375",
    "G#:375",
    "G#:375",
    "F#:375",
    "F#:375",
    "F:375",
    "F:375",
    "F#:675",
    "F#:524",
    "F#:224",
    "F#:675",
    "G#:675",
    "F#:375 A#:375",
    "F#:375 A#:375",
    "F#:224 A#:224",
    "F#:224 B:224",
    "F#:375 A#:375",
    "C#:524 G#:524",
    "A#:149",
    "G#:149",
    "F#:524",
    "F#:224",
    "F#:675 A#:675",
    "F#:524",
    "F#:224",
    "F#:525",
    "E+:150",
    "D+:150",
    "G#:675",
    "F#:675 A#:675",
    "F#:374 B:374",
    "F#:374 A#:374",
    "G#:675",
    "F#:675",
    "C#+:675 F#+:675",
    "C#+:675 G#+:675",
    "C#+:675 G#+:675",
    "C#+:675 F#+:675",
    "C#+:675 A#+:675",
    "C#+:675 G#+:675",
    "C#+:675 B+:675",
    "C#+:675 A#+:675",
    "C#+:675 F#+:675",
    "C#+:675 G#+:675",
    "C#+:675 G#+:675",
    "C#+:675 F#+:675",
    "C#+:675 A#+:675",
    "C#+:675 G#+:675",
    "C#+:675 B+:675",
    "C#+:675 A#+:675",
    "C#+:374 A+:374",
    "A+:374",
    "F#:374 B:374",
    "G#+:374",
    "F#:374 A#:374",
    "F#+:374",
    "C#:374 G#:374",
    "E+:374",
    "F#:374 B:374",
    "G#+:374",
    "F#:374 A#:374",
    "F#+:374",
    "C#:374 G#:374",
    "E+:374",
    "C#:374 F#:374",
    "D+:374",
    "A+:374 F#+:374",
    "F#+:374",
    "G#+:374 F#+:374",
    "E+:374",
    "F#+:374 D#+:374",
    "D+:374",
    "F+:374 C#+:374",
    "C#+:374",
    "F#:675",
    "F#:525",
    "F#:224",
    "F#:675",
    "G#:675",
    "F#:374 A#:374",
    "F#:224 A#:224",
    "F#:224 A#:224",
    "F#:224 A#:224",
    "F#:224 B:224",
    "F#:374 A#:374",
    "G#:675",
    "F#:675",
    "F#:675 A#:675",
    "F#:525",
    "F#:224",
    "F#:525",
    "E+:150",
    "D+:150",
    "G#:675",
    "F#:374 A#:374",
    "F#:374 A#:374",
    "F#:374 B:374",
    "F#:374 A#:374",
    "G#:675",
    "F#:675",
    "C#+:675 F#+:675",
    "C#+:675 G#+:675",
    "C#+:675 G#+:675",
    "C#+:674 F#+:674",
    "C#+:674 A#+:674",
    "C#+:674 G#+:674",
    "C#+:674 B+:674",
    "C#+:674 A#+:674",
    "C#+:674 F#+:674",
    "C#+:674 G#+:674",
    "C#+:674 G#+:674",
    "C#+:674 F#+:674",
    "C#+:674 A#+:674",
    "C#+:674 G#+:674",
    "C#+:674 B+:674",
    "C#+:674 A#+:674",
    "C#+:374 A+:374",
    "A+:374",
    "F#:374 B:374",
    "G#+:374",
    "F#:374 A#:374",
    "F#+:374",
    "C#:374 G#:374",
    "E+:374",
    "F#:374 B:374",
    "G#+:374",
    "F#:374 A#:374",
    "F#+:374",
    "C#:374 G#:374",
    "E+:374",
    "C#:374 F#:374",
    "D+:374",
    "A+:374 F#+:374",
    "F#+:374",
    "G#+:374 F#+:374",
    "E+:374",
    "F#+:374 D#+:374",
    "D+:374",
    "F+:374 C#+:374",
    "C#+:374",
    "F#+:4874",
    "C#+:674 F#+:674",
    "C#+:674 F#+:674",
    "F#:674",
    "G#:674",
    "F#:674 B:674",
    "F#:674",
    "F#:525",
    "E+:150",
    "D+:150",
    "G#:674",
    "C#+:674 F#+:674",
    "F#:674",
    "B:674",
    "G#:674",
    "C#:2175",
    "A#:150",
    "A#:150",
    "A#:150",
    "A#:2550",
    "F#:1125 A#:1125",
    "B:225",
    "C#+:975",
    "A#:150",
    "A#:150",
    "C#+:150",
    "D+:150",
    "E+:225",
    "D+:225",
    "C#+:225",
    "B:225",
    "A#:225",
    "B:225",
    "C#+:225",
    "A#:225",
    "A#:225",
    "B:225",
    "C#+:225",
    "D+:225",
    "C#+:225",
    "B:225",
    "C#+:225",
    "B:225",
    "F#:1125 A#:1125",
    "B:225",
    "C#+:975",
    "A#:150",
    "A#:150",
    "C#+:150",
    "D+:150",
    "E+:225",
    "D+:225",
    "C#+:225",
    "B:225",
    "A#:225",
    "B:225",
    "C#+:225",
    "A#:225",
    "A#:225",
    "B:225",
    "C#+:225",
    "D+:225",
    "C#+:225",
    "B:225",
    "C#+:225",
    "B:225",
    "F#:150 A:150",
    "A:150",
    "A:150",
    "A:150",
    "F#:374",
    "F:150 A:150",
    "A:150",
    "A:150",
    "A:150",
    "F:374",
    "G#:150 A:150",
    "A:150",
    "A:150",
    "A:150",
    "G#:374",
    "F#:150 A:150",
    "A:150",
    "A:150",
    "A:150",
    "F#:374",
    "A#:150 A:150",
    "A:150",
    "A:150",
    "A:150",
    "A#:374",
    "G#:150 A:150",
    "A:150",
    "A:150",
    "A:150",
    "G#:374",
    "B:150 A:150",
    "A:150",
    "A:150",
    "A:150",
    "B:374",
    "A#:150 A:150",
    "A:150",
    "A:150",
    "A:150",
    "A#:374",
    "F#:150 A:150",
    "A:150",
    "A:150",
    "A:150",
    "F#:374",
    "F:150 A:150",
    "A:150",
    "A:150",
    "A:150",
    "F:374",
    "G#:150 A:150",
    "A:150",
    "A:150",
    "A:150",
    "G#:374",
    "F#:150 A:150",
    "A:150",
    "A:150",
    "A:150",
    "F#:374",
    "A#:150 A:150",
    "A:150",
    "A:150",
    "A:150",
    "A#:374",
    "G#:150 A:150",
    "A:150",
    "A:150",
    "A:150",
    "G#:374",
    "B:150 A:150",
    "A:150",
    "A:150",
    "A:150",
    "B:374",
    "A#:150 A:150",
    "A:150",
    "A:150",
    "A:150",
    "A#:374",
    "C#+:674 F#+:674",
    "C#+:674 F#+:674",
    "A:674",
    "A:674",
    "B:674",
    "A:674",
    "B:674",
    "A:674",
    "C#+:674 F#+:674",
    "A:674",
    "B:674",
    "G#:674",
    "C#:4874",
    "F#+:674",
    "E+:674 F#+:674",
    "D+:674 G#+:674",
    "C#+:674 G#+:674",
    "B:674",
    "C#+:674 G#+:674",
    "D+:674 F#+:674",
    "C#+:674 F#+:674",
    "E+:674 A+:674",
    "C#+:674 A+:674",
    "F+:674 B+:674",
    "C#+:3075 G#+:3075",
    "B:225",
    "E:225",
    "B:225",
    "E:225",
    "C#+:225 C#+:225",
    "E:225",
    "C#+:225",
    "E:225",
    "C#+:225",
    "E:225",
    "C#+:225",
    "E:225",
    "C#+:225",
    "E:225",
    "C#+:225",
    "E:225",
    "D+:225 D+:225",
    "E:225",
    "D+:225",
    "E:225",
    "C#+:225 C#+:225",
    "E:225",
    "C#+:225",
    "E:225",
    "B:225 B:225",
    "E:225",
    "C#+:225 C#+:225",
    "B:225 B:225",
    "A#:674 F#:674 A#:674"
  ]
}