{
  "name": "Interstellar",
  "artist": "Hans Zimmer",
  "transcriber": "paninibolo",
  "instrument": "Harp",
  "notes": [
    "A-:333",
    "E-:333",
    "B-:333",
    "E-:333",
    "C^-:333",
    "E-:333",
    "B-:333",
    "E-:333",
    "A-:333",
    "E-:333",
    "C^-:333",
    "E-:333",
    "B-:333",
    "E-:333",
    "A-:333",
    "E-:333",
    "G-:333",
    "E-:333",
    "A-:333",
    "E-:333",
    "B-:333",
    "E-:333",
    "B-:333",
    "E-:333",
    "A-:333",
    "E-:333",
    "G-:333",
    "E-:333",
    "A-:333",
    "E-:333",
    "B-:333",
    "E-:333",
    "E-:333",
    "E-:333",
    "E-:333",
    "C-:333 F-:333 A-:333",
    "E:333",
    "C-:333 F-:333 A-:333",
    "E:333",
    "E-:333 G-:333 B-:333",
    "E:333",
    "E-:333 G-:333 B-:333",
    "E:333",
    "E-:333 A-:333 C^-:333",
    "E:333",
    "E-:333 A-:333 C^-:333",
    "E:333",
    "E-:333 G-:333",
    "D:333",
    "E:333",
    "D:333",
    "E:333",
    "B-:333",
    "C:333 F:333 A:333",
    "E+:333",
    "C:333 F:333 A:333",
    "E+:333",
    "E:333 G:333 B:333",
    "E+:333",
    "E:333 G:333 B:333",
    "E+:333",
    "E:333 A:333 C^:333",
    "E+:333",
    "E:333 A:333 C^:333",
    "E+:333",
    "E:333 G:333",
    "D+:333",
    "E+:333",
    "D+:333",
    "E+:333",
    "B:333",
    "C-:333 F-:333 A-:333",
    "E:333",
    "C-:333 F-:333 A-:333",
    "E:333",
    "E-:333 G-:333 B-:333",
    "E:333",
    "E-:333 G-:333 B-:333",
    "E:333",
    "E-:333 A-:333 C^-:333",
    "E:333",
    "E-:333 A-:333 C^-:333",
    "E:333",
    "E-:333 G-:333",
    "D:333",
    "E:333",
    "D:333",
    "E:333",
    "B-:333",
    "C:333 F:333 A:333",
    "E+:333",
    "C:333 F:333 A:333",
    "E+:333",
    "E:333 G:333 B:333",
    "E+:333",
    "E:333 G:333 B:333",
    "E+:333",
    "E:333 A:333 C^:333",
    "E+:333",
    "E:333 A:333 C^:333",
    "E+:333",
    "E:333 G:333",
    "D+:333",
    "E+:333",
    "D+:333",
    "E+:333",
    "B:333"
  ],
  "id": "4fa1a02f-925c-43cf-bd0c-41281572d548"
}
